quickcal/__init__.py
quickcal-0.0.1.dist-info/LICENSE
quickcal-0.0.1.dist-info/METADATA
quickcal-0.0.1.dist-info/WHEEL
quickcal-0.0.1.dist-info/top_level.txt
quickcal-0.0.1.dist-info/RECORD
